LICENSE
MANIFEST.in
README.md
README.rst
setup.py
torchcluster/__init__.py
torchcluster.egg-info/PKG-INFO
torchcluster.egg-info/SOURCES.txt
torchcluster.egg-info/dependency_links.txt
torchcluster.egg-info/top_level.txt
torchcluster/dataset/__init__.py
torchcluster/dataset/base.py
torchcluster/dataset/simple.py
torchcluster/helper/__init__.py
torchcluster/helper/distance.py
torchcluster/zoo/__init__.py
torchcluster/zoo/base.py
torchcluster/zoo/k_means.py
torchcluster/zoo/spectrum.py