Metadata-Version: 1.0
Name: torchcluster
Version: 0.1.4
Summary: Torchcluster is a python package for cluster analysis.
Home-page: https://github.com/tczhangzhi/cluster
Author: Zhi Zhang
Author-email: 850734033@qq.com
License: MIT
Keywords: pytorch,cluster
Platform: UNKNOWN
